deltachat/contact.py
deltachat/const.py
deltachat/events.py
deltachat/direct_imap.py
deltachat/reactions.py
deltachat/capi.abi3.so
deltachat/props.py
deltachat/tracker.py
deltachat/py.typed
deltachat/hookspec.py
deltachat/provider.py
deltachat/message.py
deltachat/testplugin.py
deltachat/cutil.py
deltachat/chat.py
deltachat/account.py
deltachat/_build.py
deltachat/__init__.py
deltachat.libs/libgcc_s-4e37474d.so.1
deltachat-1.155.6.dist-info/entry_points.txt
deltachat-1.155.6.dist-info/RECORD
deltachat-1.155.6.dist-info/top_level.txt
deltachat-1.155.6.dist-info/LICENSE
deltachat-1.155.6.dist-info/WHEEL
deltachat-1.155.6.dist-info/METADATA
